markdown_it/__init__.py
markdown_it/_punycode.py
markdown_it/main.py
markdown_it/parser_block.py
markdown_it/parser_core.py
markdown_it/parser_inline.py
markdown_it/port.yaml
markdown_it/py.typed
markdown_it/renderer.py
markdown_it/ruler.py
markdown_it/token.py
markdown_it/tree.py
markdown_it/utils.py
markdown_it/cli/__init__.py
markdown_it/cli/parse.py
markdown_it/common/__init__.py
markdown_it/common/entities.py
markdown_it/common/html_blocks.py
markdown_it/common/html_re.py
markdown_it/common/normalize_url.py
markdown_it/common/utils.py
markdown_it/helpers/__init__.py
markdown_it/helpers/parse_link_destination.py
markdown_it/helpers/parse_link_label.py
markdown_it/helpers/parse_link_title.py
markdown_it/presets/__init__.py
markdown_it/presets/commonmark.py
markdown_it/presets/default.py
markdown_it/presets/zero.py
markdown_it/rules_block/__init__.py
markdown_it/rules_block/blockquote.py
markdown_it/rules_block/code.py
markdown_it/rules_block/fence.py
markdown_it/rules_block/heading.py
markdown_it/rules_block/hr.py
markdown_it/rules_block/html_block.py
markdown_it/rules_block/lheading.py
markdown_it/rules_block/list.py
markdown_it/rules_block/paragraph.py
markdown_it/rules_block/reference.py
markdown_it/rules_block/state_block.py
markdown_it/rules_block/table.py
markdown_it/rules_core/__init__.py
markdown_it/rules_core/block.py
markdown_it/rules_core/inline.py
markdown_it/rules_core/linkify.py
markdown_it/rules_core/normalize.py
markdown_it/rules_core/replacements.py
markdown_it/rules_core/smartquotes.py
markdown_it/rules_core/state_core.py
markdown_it/rules_inline/__init__.py
markdown_it/rules_inline/autolink.py
markdown_it/rules_inline/backticks.py
markdown_it/rules_inline/balance_pairs.py
markdown_it/rules_inline/emphasis.py
markdown_it/rules_inline/entity.py
markdown_it/rules_inline/escape.py
markdown_it/rules_inline/html_inline.py
markdown_it/rules_inline/image.py
markdown_it/rules_inline/link.py
markdown_it/rules_inline/newline.py
markdown_it_py-2.0.1.dist-info/LICENSE
markdown_it_py-2.0.1.dist-info/METADATA
markdown_it_py-2.0.1.dist-info/WHEEL
markdown_it_py-2.0.1.dist-info/entry_points.txt
markdown_it_py-2.0.1.dist-info/top_level.txt
markdown_it_py-2.0.1.dist-info/RECORD
