Metadata-Version: 2.1
Name: markdown-it-py
Version: 2.0.1
Summary: Python port of markdown-it. Markdown parsing, done right!
Home-page: https://github.com/executablebooks/markdown-it-py
Author: Chris Sewell
Author-email: chrisj_sewell@hotmail.com
License: MIT
Project-URL: Documentation, https://markdown-it-py.readthedocs.io
Keywords: markdown lexer parser development
Platform: UNKNOWN
Classifier: Development Status :: 5 - Production/Stable
Classifier: Intended Audience :: Developers
Classifier: License :: OSI Approved :: MIT License
Classifier: Programming Language :: Python :: 3
Classifier: Programming Language :: Python :: 3.6
Classifier: Programming Language :: Python :: 3.7
Classifier: Programming Language :: Python :: 3.8
Classifier: Programming Language :: Python :: 3.9
Classifier: Programming Language :: Python :: 3.10
Classifier: Programming Language :: Python :: Implementation :: CPython
Classifier: Programming Language :: Python :: Implementation :: PyPy
Classifier: Topic :: Software Development :: Libraries :: Python Modules
Classifier: Topic :: Text Processing :: Markup
Requires-Python: ~=3.6
Provides-Extra: code_style
Provides-Extra: compare
Provides-Extra: linkify
Provides-Extra: plugins
Provides-Extra: rtd
Provides-Extra: testing
Provides-Extra: benchmarking
License-File: LICENSE
